<?xml version="1.0" encoding="utf-8" ?><dwsync><file name=".htaccess" server="kick01.sakura.ne.jp//" local="3615258219" remote="3614664900" Dst="-1" /><file name="LICENSE.txt" server="kick01.sakura.ne.jp//" local="3615258219" remote="3614664900" Dst="-1" /><file name="akismet.php" server="kick01.sakura.ne.jp//" local="3615258231" remote="3614664900" Dst="-1" /><file name="class.akismet-cli.php" server="kick01.sakura.ne.jp//" local="3615258242" remote="3614664900" Dst="-1" /><file name="class.akismet-admin.php" server="kick01.sakura.ne.jp//" local="3615258242" remote="3614664900" Dst="-1" /><file name="class.akismet-rest-api.php" server="kick01.sakura.ne.jp//" local="3615258245" remote="3614664900" Dst="-1" /><file name="class.akismet-widget.php" server="kick01.sakura.ne.jp//" local="3615258245" remote="3614664900" Dst="-1" /><file name="index.php" server="kick01.sakura.ne.jp//" local="3615258249" remote="3614664900" Dst="-1" /><file name="class.akismet.php" server="kick01.sakura.ne.jp//" local="3615258249" remote="3614664900" Dst="-1" /><file name="readme.txt" server="kick01.sakura.ne.jp//" local="3615258254" remote="3614664900" Dst="-1" /><file name="wrapper.php" server="kick01.sakura.ne.jp//" local="3615258265" remote="3614664900" Dst="-1" /></dwsync>